validpeas/__init__.py
validpeas/py.typed
validpeas-0.2.dist-info/LICENSE
validpeas-0.2.dist-info/METADATA
validpeas-0.2.dist-info/WHEEL
validpeas-0.2.dist-info/top_level.txt
validpeas-0.2.dist-info/RECORD
