Metadata-Version: 2.1
Name: validpeas
Version: 0.2
Summary: Tools for structured validations
Home-page: https://github.com/jmriddell/validpeas
Author: Juan Ezequiel Molina Riddell
Author-email: jmriddell@protonmain.ch
Keywords: validation
Classifier: Development Status :: 3 - Alpha
Classifier: Intended Audience :: Developers
Classifier: License :: OSI Approved :: MIT License
Classifier: Programming Language :: Python :: 3.11
License-File: LICENSE
Requires-Dist: pydantic
